YTVdownload/__init__.py
YTVdownload-1.0.1.dist-info/LICENCE
YTVdownload-1.0.1.dist-info/METADATA
YTVdownload-1.0.1.dist-info/WHEEL
YTVdownload-1.0.1.dist-info/top_level.txt
YTVdownload-1.0.1.dist-info/RECORD
