Metadata-Version: 2.1
Name: YTVdownload
Version: 1.0.1
Summary: This package can Download YouTube videos in MP3 or MP4 format....
Home-page: https://github.com/alphacodingat/YTVdownload.git
Author: Akshat Tiwari
Author-email: thealphacoding@gmail.com
License: UNKNOWN
Platform: UNKNOWN
Classifier: Programming Language :: Python :: 3
Classifier: License :: OSI Approved :: MIT License
Classifier: Operating System :: OS Independent
Requires-Python: >=3.2
Requires-Dist: pafy
